full_adder.v
// Full adder design using verilog primitive gates
// P W Nutter (based on a design by Jeff Pepper)
// Date 20/8/2021
// 
// Do not touch the following line it is required for simulation 
// All gates have a 1ns delay (#1 = 1ns)
`timescale 1ns/100ps

// for simulation purposes, do not delete
`default_nettype none

//Module definition

module full_adder(input  wire  a, 
                  input  wire  b, 
                  input  wire  cin, 
                  output wire  s, 
                  output wire  cout);

// Internal connections should be defined here
wire axorb; // Will be the output of a^b
wire ab; // Will be the output of a.b
wire cin_axorb; // Will be the output cin.(a^b)

// Sum logic for full adder s=(a^b)^cin
xor #1 gate1 (axorb, a, b);
xor #1 gate2 (s, cin, axorb);

// Carry logic for full adder cout=cin.(a^b) + a.b
and #1 gate3 (ab, a, b);
and #1 gate4 (cin_axorb, cin, axorb);
or #1 gate5 (cout, cin_axorb, ab);



endmodule 

// for simulation purposes, do not delete
`default_nettype wire

adder_4bit.v
// 4-bit adder design using verilog primitive gates
// P W Nutter (based on a design by Jeff Pepper)
// Date 20/8/2021
// 

// Do not touch the following line it is required for simulation 
`timescale 1ns/100ps

// for simulation purposes, do not delete
`default_nettype none

//Module definition

module adder_4bit(input  wire [3:0]  a, 
                  input  wire [3:0]  b, 
                  input  wire        cin, 
                  output wire [3:0]  s, 
                  output wire        cout);

//Internal carry connections
wire c0;
wire c1;
wire c2;

// Instantiate 4 x full_adder
full_adder adder0 (a[0], b[0], cin, s[0], c0);
full_adder adder1 (a[1], b[1], c0, s[1], c1);
full_adder adder2 (a[2], b[2], c1, s[2], c2);
full_adder adder3 (a[3], b[3], c2, s[3], cout);





endmodule 

// for simulation purposes, do not delete
`default_nettype wire

adder_4bit_tb.v
// 4-bit adder testbench
// P W Nutter (based on a design by Jeff Pepper)
// Date 20/8/2021

// #1 = 1ns
`timescale 1ns/100ps 

module adder_4bit_tb();

// Internal connections
reg [3:0] a;
reg [3:0] b;
reg       cin;
wire [3:0] s;
wire cout;

// Instantiate adder_4bit as dut (device under test)

adder_4bit dut(a, b, cin, s, cout);

// Test vectors
initial
begin
// Enter you stimulus below this line
// Using 14 test vectors the interconnect of the 4bit added can be verified

// Check all fulladders are connected to something, s=0 cout=0 not Xs
//If a tristate (Z) or unknown state (X) we know we have some sort of physical connection issue intially and not a logical connection issue yet/not at all
#100 a='b0000; b='b0000; cin=0;
// Check connections for a[0], b[0], cin, S[0], S=0001 cout=0
#100 a='b0001; b='b0000; cin=0;
#100 a='b0000; b='b0001; cin=0;
#100 a='b0000; b='b0000; cin=1;
// Check connection of carry out of the first adder
#100 a='b0001; b='b0001; cin=0;
// Check connections for a[1], b[1], c[1]
#100 a='b0010; b='b0000; cin=0;
#100 a='b0000; b='b0010; cin=0;
// ADD 7 MORE TESTS TO COMPLETE CONNECTIVITY TESTS
// for each add your test vectors before the semicolon after the delay
#100 a='b0010; b='b0010; cin=0; //I am testing if the carry bit of the second full adder is connected to the third full adder correctly a postive result would indicate the s2 would be 1
//Checking the connections for what a[2], b[2], c[2] and they should if connected correctly produce s2 = 1
#100 a='b0100; b='b0000; cin = 0;
#100 a='b0000; b='b0100; cin = 0;
//We are checking the carry wire coming out of full bit adder 3 is connected to full bit adder 4 correctly as full bit adder 3 would produce a cout/ c[2] of 1 and it would be fed to full adder 4 as cin input and a=0 and b=0 so it should produce a s[3] of 1 if the wire inbetween them are connected correctly
#100 a='b0100; b='b0100; cin = 0;
//Checking the connections for what a[3], b[3], c[3] and they should if connected correctly produce s3 = 1
#100 a='b1000; b='b0000; cin = 0;
#100 a='b0000; b='b1000; cin = 0;

#100 a='b1000; b='b1000; cin=0;

// Connectivity tests completed.

// ADD TESTS FOR FINDING MAXIMUM CARRY DELAY HERE
// 2 test vectors required - one to initialise followed by the 2nd to exercise
// the critical path
#100 a='b0000; b='b0000; cin=0;
#100 a='b1111; b='b0000; cin=1;

// Please make sure your stimulus is above this line
// delay for end of wave traces to be visible
#100 $finish; // exit the simulation
end
 
 
// Save results as VCD file 
// Do not change
initial
 begin
  $dumpfile("adder_4bit_tb_results.vcd");  // Save simulation waveforms in this file
  $dumpvars; // Capture all simulation waveforms
 end

endmodule

adder_4bit_tb_results.vcd
$date
	Tue Oct 19 16:54:37 2021
$end
$version
	Icarus Verilog
$end
$timescale
	100ps
$end
$scope module adder_4bit_tb $end
$var wire 4 ! s [3:0] $end
$var wire 1 " cout $end
$var reg 4 # a [3:0] $end
$var reg 4 $ b [3:0] $end
$var reg 1 % cin $end
$scope module dut $end
$var wire 4 & a [3:0] $end
$var wire 4 ' b [3:0] $end
$var wire 1 % cin $end
$var wire 4 ( s [3:0] $end
$var wire 1 " cout $end
$var wire 1 ) c2 $end
$var wire 1 * c1 $end
$var wire 1 + c0 $end
$scope module adder0 $end
$var wire 1 , a $end
$var wire 1 - ab $end
$var wire 1 . axorb $end
$var wire 1 / b $end
$var wire 1 % cin $end
$var wire 1 0 cin_axorb $end
$var wire 1 + cout $end
$var wire 1 1 s $end
$upscope $end
$scope module adder1 $end
$var wire 1 2 a $end
$var wire 1 3 ab $end
$var wire 1 4 axorb $end
$var wire 1 5 b $end
$var wire 1 + cin $end
$var wire 1 6 cin_axorb $end
$var wire 1 * cout $end
$var wire 1 7 s $end
$upscope $end
$scope module adder2 $end
$var wire 1 8 a $end
$var wire 1 9 ab $end
$var wire 1 : axorb $end
$var wire 1 ; b $end
$var wire 1 * cin $end
$var wire 1 < cin_axorb $end
$var wire 1 ) cout $end
$var wire 1 = s $end
$upscope $end
$scope module adder3 $end
$var wire 1 > a $end
$var wire 1 ? ab $end
$var wire 1 @ axorb $end
$var wire 1 A b $end
$var wire 1 ) cin $end
$var wire 1 B cin_axorb $end
$var wire 1 " cout $end
$var wire 1 C s $end
$upscope $end
$upscope $end
$upscope $end
$enddefinitions $end
#0
$dumpvars
xC
xB
xA
x@
x?
x>
x=
x<
x;
x:
x9
x8
x7
x6
x5
x4
x3
x2
x1
x0
x/
x.
x-
x,
x+
x*
x)
bx (
bx '
bx &
x%
bx $
bx #
x"
bx !
$end
#1000
0/
05
0;
0A
0,
02
08
0>
0%
b0 $
b0 '
b0 #
b0 &
#1010
0.
0-
04
03
0:
09
0@
0?
00
#1020
bx0 !
bx0 (
01
06
0<
0B
0+
#1030
0*
0)
0"
bx00 !
bx00 (
07
#1040
0=
b0 !
b0 (
0C
#2000
1,
b1 #
b1 &
#2010
1.
#2020
b1 !
b1 (
11
#3000
1/
0,
b1 $
b1 '
b0 #
b0 &
#4000
0/
1%
b0 $
b0 '
#4010
0.
b0 !
b0 (
01
10
#4020
b1 !
b1 (
11
00
1+
#4030
0+
b11 !
b11 (
17
#4040
b1 !
b1 (
07
#5000
1/
1,
0%
b1 $
b1 '
b1 #
b1 &
#5010
1-
b0 !
b0 (
01
#5020
1+
#5030
b10 !
b10 (
17
#6000
0/
0,
12
b0 $
b0 '
b10 #
b10 &
#6010
0-
14
#6020
0+
b0 !
b0 (
07
16
#6030
b10 !
b10 (
17
06
1*
#6040
0*
b110 !
b110 (
1=
#6050
b10 !
b10 (
0=
#7000
15
02
b10 $
b10 '
b0 #
b0 &
#8000
12
b10 #
b10 &
#8010
04
13
#8020
b0 !
b0 (
07
1*
#8030
b100 !
b100 (
1=
#9000
05
02
18
b0 $
b0 '
b100 #
b100 &
#9010
03
1:
#9020
0*
b0 !
b0 (
0=
1<
#9030
b100 !
b100 (
1=
0<
1)
#9040
0)
b1100 !
b1100 (
1C
#9050
b100 !
b100 (
0C
#10000
1;
08
b100 $
b100 '
b0 #
b0 &
#11000
18
b100 #
b100 &
#11010
0:
19
#11020
b0 !
b0 (
0=
1)
#11030
b1000 !
b1000 (
1C
#12000
0;
08
1>
b0 $
b0 '
b1000 #
b1000 &
#12010
09
1@
#12020
0)
b0 !
b0 (
0C
1B
#12030
b1000 !
b1000 (
1C
0B
1"
#12040
0"
#13000
1A
0>
b1000 $
b1000 '
b0 #
b0 &
#14000
1>
b1000 #
b1000 &
#14010
0@
1?
#14020
b0 !
b0 (
0C
1"
#15000
0A
0>
b0 $
b0 '
b0 #
b0 &
#15010
0?
#15020
0"
#16000
1,
12
18
1>
1%
b1111 #
b1111 &
#16010
1.
14
1:
1@
b1 !
b1 (
11
#16020
01
10
17
1=
b1110 !
b1110 (
1C
#16030
1+
#16040
b1100 !
b1100 (
07
16
#16050
1*
#16060
b1000 !
b1000 (
0=
1<
#16070
1)
#16080
b0 !
b0 (
0C
1B
#16090
1"
